src/__init__.py
src/__main__.py
src/app.py
src/config.py
src/server.py
src/middleware/__init__.py
src/middleware/paths.py
src/middleware/preflight.py
src/middleware/prompt_storage.py
src/middleware/reflection_config.py
src/middleware/reflection_middleware.py
src/middleware/reflection_store.py
src/middleware/reflection_transform.py
src/models/__init__.py
src/models/catalog.py
src/models/resourceref.py
src/models/workspace_summary.py
src/models/raster/__init__.py
src/models/raster/convert.py
src/models/raster/info.py
src/models/raster/reproject.py
src/models/raster/stats.py
src/models/vector/__init__.py
src/models/vector/buffer.py
src/models/vector/clip.py
src/models/vector/convert.py
src/models/vector/info.py
src/models/vector/reproject.py
src/models/vector/simplify.py
src/prompts/__init__.py
src/prompts/aggregation.py
src/prompts/crs.py
src/prompts/hydrology.py
src/prompts/justification.py
src/prompts/resampling.py
src/prompts/risk.py
src/resources/__init__.py
src/resources/catalog/__init__.py
src/resources/catalog/all.py
src/resources/catalog/base.py
src/resources/catalog/by_crs.py
src/resources/catalog/raster.py
src/resources/catalog/summary.py
src/resources/catalog/vector.py
src/resources/metadata/__init__.py
src/resources/metadata/band.py
src/resources/metadata/format_detection.py
src/resources/metadata/raster.py
src/resources/metadata/statistics.py
src/resources/metadata/vector.py
src/resources/reference/__init__.py
src/resources/reference/compression.py
src/resources/reference/crs.py
src/resources/reference/glossary.py
src/resources/reference/resampling.py
src/shared/__init__.py
src/shared/catalog/__init__.py
src/shared/catalog/crs_filter.py
src/shared/catalog/scanner.py
src/shared/catalog/summary.py
src/shared/enum/__init__.py
src/shared/enum/direction.py
src/shared/enum/float.py
src/shared/enum/percentile.py
src/shared/enum/string.py
src/shared/metadata/__init__.py
src/shared/metadata/format_detection.py
src/shared/raster/__init__.py
gdal_mcp-1.1.3.dist-info/METADATA
gdal_mcp-1.1.3.dist-info/WHEEL
gdal_mcp-1.1.3.dist-info/entry_points.txt
gdal_mcp-1.1.3.dist-info/licenses/LICENSE
gdal_mcp-1.1.3.dist-info/RECORD
