Metadata-Version: 2.4
Name: gdal-mcp
Version: 1.1.3
Summary: FastMCP server for Python-native GDAL ops (Rasterio/PyProj/pyogrio|Fiona/Shapely)
Project-URL: Homepage, https://github.com/Wayfinder-Foundry/gdal-mcp
Project-URL: Documentation, https://github.com/Wayfinder-Foundry/gdal-mcp
Author: GDAL MCP Team
License: MIT License
License-File: LICENSE
Keywords: GIS,QGIS,fastmcp,gdal,geomatics,geospatial,mcp,raster,remote sensing
Requires-Python: >=3.11
Requires-Dist: fastmcp<3.0,>=2.0
Requires-Dist: fiona>=1.10.1
Requires-Dist: geopandas>=1.1.1
Requires-Dist: markdown-it-py>=3.0.0
Requires-Dist: numpy>=2.2.6
Requires-Dist: pydantic>=2.0
Requires-Dist: pyogrio>=0.7
Requires-Dist: pyproj>=3.6
Requires-Dist: python-frontmatter>=1.0.0
Requires-Dist: pyyaml>=6.0
Requires-Dist: rasterio>=1.3
Requires-Dist: rich>=13.0
Requires-Dist: shapely>=2.0
Requires-Dist: typer>=0.12
Provides-Extra: dev
Requires-Dist: mypy>=1.10; extra == 'dev'
Requires-Dist: pre-commit>=3.6; extra == 'dev'
Requires-Dist: pytest-asyncio>=0.23; extra == 'dev'
Requires-Dist: pytest>=8.0; extra == 'dev'
Requires-Dist: ruff>=0.5; extra == 'dev'
Requires-Dist: types-pyyaml>=6.0.0.20240917; extra == 'dev'
